{"pages":{"welcome":{"name":"Welcome","title":"Performance","route":{"url":"\/","auth":false,"controller":"PagesController"},"nav":{"hidden":true,"name":"Home","class":null},"template":{"id":1,"blade":"default"},"type":"get","uuid":"709576a0-999d-4785-8d53-f50c5383d89f","hidden":true},"about":{"name":"Over ons","title":"Over ons","route":{"url":"\/about","auth":false,"controller":"PagesController"},"nav":{"hidden":false,"name":"Over ons","class":null},"template":{"id":1,"blade":"about"},"type":"get","uuid":"d90c8946-8420-4956-bf41-1213b8ca66f8","hidden":false},"activities":{"name":"Activiteiten","title":"Activiteiten","route":{"url":"\/activities","auth":false,"controller":"PagesController"},"nav":{"hidden":false,"name":"Activiteiten","class":null},"template":{"id":1,"blade":"activities"},"type":"get","uuid":"d53b3818-3dac-421f-bf89-9f97027f365f","hidden":false},"portfolio":{"name":"Portfolio","title":"Portfolio","route":{"url":"\/portfolio","auth":false,"controller":"PagesController"},"nav":{"hidden":false,"name":"Portfolio","class":null},"template":{"id":1,"blade":"portfolio"},"type":"get","uuid":"f06e7637-4e41-4d72-99dd-c3448ccb83b9","hidden":false},"contact":{"name":"Contact","title":"Contact","route":{"url":"\/contact","auth":false,"controller":"PagesController"},"nav":{"hidden":false,"name":"Contact","class":"btn btn-primary text-white"},"template":{"id":1,"blade":"default"},"type":"get","uuid":"b44dbb1d-68e4-4eaf-9dc9-e66d35a5df5b","hidden":false},"voorwaarden":{"name":"Voorwaarden","title":"Voorwaarden","route":{"url":"\/voorwaarden","auth":false,"controller":"PagesController"},"template":{"id":1,"blade":"default"},"nav":{"hidden":true,"name":"Voorwaarden","class":null},"type":"get","uuid":"23d1ae76-b2de-412b-afd4-e3cd2d85e8f7","hidden":false}}}